coinbase/__init__.py
coinbase/__version__.py
coinbase/api_base.py
coinbase/constants.py
coinbase/jwt_generator.py
coinbase/rest/__init__.py
coinbase/rest/accounts.py
coinbase/rest/convert.py
coinbase/rest/data_api.py
coinbase/rest/fees.py
coinbase/rest/futures.py
coinbase/rest/market_data.py
coinbase/rest/orders.py
coinbase/rest/payments.py
coinbase/rest/perpetuals.py
coinbase/rest/portfolios.py
coinbase/rest/products.py
coinbase/rest/public.py
coinbase/rest/rest_base.py
coinbase/rest/types/__init__.py
coinbase/rest/types/accounts_types.py
coinbase/rest/types/base_response.py
coinbase/rest/types/common_types.py
coinbase/rest/types/convert_types.py
coinbase/rest/types/data_api_types.py
coinbase/rest/types/fees_types.py
coinbase/rest/types/futures_types.py
coinbase/rest/types/orders_types.py
coinbase/rest/types/payments_types.py
coinbase/rest/types/perpetuals_types.py
coinbase/rest/types/portfolios_types.py
coinbase/rest/types/product_types.py
coinbase/rest/types/public_types.py
coinbase/websocket/__init__.py
coinbase/websocket/channels.py
coinbase/websocket/websocket_base.py
coinbase/websocket/types/__init__.py
coinbase/websocket/types/base_response.py
coinbase/websocket/types/misc_types.py
coinbase/websocket/types/websocket_response.py
tests/rest/__init__.py
tests/rest/serialize.py
tests/rest/test_accounts.py
tests/rest/test_convert.py
tests/rest/test_data_api.py
tests/rest/test_fees.py
tests/rest/test_futures.py
tests/rest/test_market_data.py
tests/rest/test_orders.py
tests/rest/test_payments.py
tests/rest/test_perpetuals.py
tests/rest/test_portfolios.py
tests/rest/test_products.py
tests/rest/test_public.py
tests/rest/test_rest_base.py
tests/websocket/__init__.py
tests/websocket/mock_ws_server.py
tests/websocket/test_channels.py
tests/websocket/test_websocket_base.py
coinbase_advanced_py-1.8.2.dist-info/LICENSE.md
coinbase_advanced_py-1.8.2.dist-info/METADATA
coinbase_advanced_py-1.8.2.dist-info/WHEEL
coinbase_advanced_py-1.8.2.dist-info/top_level.txt
coinbase_advanced_py-1.8.2.dist-info/RECORD
