Metadata-Version: 2.1
Name: coinbase-advanced-py
Version: 1.8.2
Summary: Coinbase Advanced API Python SDK
Home-page: https://github.com/coinbase/coinbase-advanced-py
Author: Coinbase
License: Apache 2.0
Keywords: Coinbase,Advanced Trade,API,Advanced API
Classifier: Intended Audience :: Developers
Classifier: Intended Audience :: Financial and Insurance Industry
Classifier: License :: OSI Approved :: Apache Software License
Classifier: Programming Language :: Python :: 3.8
Classifier: Programming Language :: Python :: 3.9
Classifier: Programming Language :: Python :: 3.10
Classifier: Programming Language :: Python :: 3.11
Requires-Python: >=3.8
License-File: LICENSE.md
Requires-Dist: requests>=2.31.0
Requires-Dist: cryptography>=42.0.4
Requires-Dist: PyJWT>=2.8.0
Requires-Dist: websockets<14.0,>=12.0
Requires-Dist: backoff>=2.2.1
Provides-Extra: test
Requires-Dist: requests-mock==1.11.0; extra == "test"
Requires-Dist: asynctest==0.13.0; extra == "test"
Provides-Extra: lint
Requires-Dist: black==24.3.0; extra == "lint"
Requires-Dist: isort==5.12.0; extra == "lint"
